LICENSE
README.md
setup.py
arfpy/__init__.py
arfpy/arf.py
arfpy/utils.py
arfpy.egg-info/PKG-INFO
arfpy.egg-info/SOURCES.txt
arfpy.egg-info/dependency_links.txt
arfpy.egg-info/requires.txt
arfpy.egg-info/top_level.txt
tests/test.py
tests/test_diabetes.py
tests/test_iris.py