Metadata-Version: 2.1
Name: arfpy
Version: 0.1.1
Summary: Adversarial random forests for density estimation and generative modeling
Home-page: https://github.com/bips-hb/arfpy
Author: Kristin Blesch, Marvin N. Wright
Author-email: blesch@leibniz-bips.de
License: MIT
Platform: UNKNOWN
Classifier: Programming Language :: Python :: 3.8
Classifier: Programming Language :: Python :: 3.9
Classifier: Programming Language :: Python :: 3.10
Classifier: Programming Language :: Python :: 3.11
